pytest_html_nova_act/__init__.py
pytest_html_nova_act/plugin.py
pytest_html_nova_act/py.typed
pytest_html_nova_act/static/nova_act_accordion.js
pytest_html_nova_act/static/nova_act_styles.css
pytest_html_nova_act/templates/action_viewer_accordion.html
pytest_html_nova_act-1.0.2.dist-info/licenses/LICENSE
pytest_html_nova_act-1.0.2.dist-info/licenses/NOTICE
pytest_html_nova_act-1.0.2.dist-info/METADATA
pytest_html_nova_act-1.0.2.dist-info/WHEEL
pytest_html_nova_act-1.0.2.dist-info/entry_points.txt
pytest_html_nova_act-1.0.2.dist-info/top_level.txt
pytest_html_nova_act-1.0.2.dist-info/RECORD
