Metadata-Version: 2.4
Name: pytest-html-nova-act
Version: 1.0.2
Summary: A Pytest Plugin for Amazon Nova Act Python SDK.
Author-email: Pytest Html Plugin for Amazon Nova Act <nova-act@amazon.com>
License-Expression: Apache-2.0
Requires-Python: >=3.10
License-File: LICENSE
License-File: NOTICE
Provides-Extra: dev
Requires-Dist: build; extra == "dev"
Requires-Dist: setuptools; extra == "dev"
Requires-Dist: twine; extra == "dev"
Requires-Dist: wheel; extra == "dev"
Dynamic: license-file
